<?xml version="1.0" encoding="UTF-8"?>
<ipxact:component xmlns:xsi="http://www.w3.org/2001/XMLSchema-instance" xmlns:ipxact="http://www.accellera.org/XMLSchema/IPXACT/1685-2014" xmlns:kactus2="http://kactus2.cs.tut.fi" xsi:schemaLocation="http://www.accellera.org/XMLSchema/IPXACT/1685-2014 http://www.accellera.org/XMLSchema/IPXACT/1685-2014/index.xsd">
	<ipxact:vendor>pulp-platform.org</ipxact:vendor>
	<ipxact:library>peripheral</ipxact:library>
	<ipxact:name>apb_spi_master</ipxact:name>
	<ipxact:version>1.0</ipxact:version>
	<ipxact:busInterfaces>
		<ipxact:busInterface>
			<ipxact:name>event</ipxact:name>
			<ipxact:busType vendor="pulp-platform.org" library="interface" name="irq" version="1.0"/>
			<ipxact:abstractionTypes>
				<ipxact:abstractionType>
					<ipxact:abstractionRef vendor="pulp-platform.org" library="interface" name="irq.absDef" version="1.0"/>
					<ipxact:portMaps>
						<ipxact:portMap>
							<ipxact:logicalPort>
								<ipxact:name>event</ipxact:name>
								<ipxact:range>
									<ipxact:left>28</ipxact:left>
									<ipxact:right>27</ipxact:right>
								</ipxact:range>
							</ipxact:logicalPort>
							<ipxact:physicalPort>
								<ipxact:name>events_o</ipxact:name>
								<ipxact:partSelect>
									<ipxact:range>
										<ipxact:left>1</ipxact:left>
										<ipxact:right>0</ipxact:right>
									</ipxact:range>
								</ipxact:partSelect>
							</ipxact:physicalPort>
						</ipxact:portMap>
					</ipxact:portMaps>
				</ipxact:abstractionType>
			</ipxact:abstractionTypes>
			<ipxact:system>
				<ipxact:group>irq_source</ipxact:group>
			</ipxact:system>
		</ipxact:busInterface>
		<ipxact:busInterface>
			<ipxact:name>spi_master</ipxact:name>
			<ipxact:busType vendor="pulp-platform.org" library="interface" name="qspi" version="1.0"/>
			<ipxact:abstractionTypes>
				<ipxact:abstractionType>
					<ipxact:abstractionRef vendor="pulp-platform.org" library="interface" name="qspi.absDef" version="1.0"/>
					<ipxact:portMaps>
						<ipxact:portMap>
							<ipxact:logicalPort>
								<ipxact:name>CLK</ipxact:name>
							</ipxact:logicalPort>
							<ipxact:physicalPort>
								<ipxact:name>spi_clk</ipxact:name>
							</ipxact:physicalPort>
						</ipxact:portMap>
						<ipxact:portMap>
							<ipxact:logicalPort>
								<ipxact:name>CSN0</ipxact:name>
							</ipxact:logicalPort>
							<ipxact:physicalPort>
								<ipxact:name>spi_csn0</ipxact:name>
							</ipxact:physicalPort>
						</ipxact:portMap>
						<ipxact:portMap>
							<ipxact:logicalPort>
								<ipxact:name>CSN1</ipxact:name>
							</ipxact:logicalPort>
							<ipxact:physicalPort>
								<ipxact:name>spi_csn1</ipxact:name>
							</ipxact:physicalPort>
						</ipxact:portMap>
						<ipxact:portMap>
							<ipxact:logicalPort>
								<ipxact:name>CSN2</ipxact:name>
							</ipxact:logicalPort>
							<ipxact:physicalPort>
								<ipxact:name>spi_csn2</ipxact:name>
							</ipxact:physicalPort>
						</ipxact:portMap>
						<ipxact:portMap>
							<ipxact:logicalPort>
								<ipxact:name>CSN3</ipxact:name>
							</ipxact:logicalPort>
							<ipxact:physicalPort>
								<ipxact:name>spi_csn3</ipxact:name>
							</ipxact:physicalPort>
						</ipxact:portMap>
						<ipxact:portMap>
							<ipxact:logicalPort>
								<ipxact:name>SDO0</ipxact:name>
							</ipxact:logicalPort>
							<ipxact:physicalPort>
								<ipxact:name>spi_sdo0</ipxact:name>
							</ipxact:physicalPort>
						</ipxact:portMap>
						<ipxact:portMap>
							<ipxact:logicalPort>
								<ipxact:name>SDO1</ipxact:name>
							</ipxact:logicalPort>
							<ipxact:physicalPort>
								<ipxact:name>spi_sdo1</ipxact:name>
							</ipxact:physicalPort>
						</ipxact:portMap>
						<ipxact:portMap>
							<ipxact:logicalPort>
								<ipxact:name>SDO2</ipxact:name>
							</ipxact:logicalPort>
							<ipxact:physicalPort>
								<ipxact:name>spi_sdo2</ipxact:name>
							</ipxact:physicalPort>
						</ipxact:portMap>
						<ipxact:portMap>
							<ipxact:logicalPort>
								<ipxact:name>SDO3</ipxact:name>
							</ipxact:logicalPort>
							<ipxact:physicalPort>
								<ipxact:name>spi_sdo3</ipxact:name>
							</ipxact:physicalPort>
						</ipxact:portMap>
						<ipxact:portMap>
							<ipxact:logicalPort>
								<ipxact:name>SDI1</ipxact:name>
							</ipxact:logicalPort>
							<ipxact:physicalPort>
								<ipxact:name>spi_sdi1</ipxact:name>
							</ipxact:physicalPort>
						</ipxact:portMap>
						<ipxact:portMap>
							<ipxact:logicalPort>
								<ipxact:name>SDI0</ipxact:name>
							</ipxact:logicalPort>
							<ipxact:physicalPort>
								<ipxact:name>spi_sdi0</ipxact:name>
							</ipxact:physicalPort>
						</ipxact:portMap>
						<ipxact:portMap>
							<ipxact:logicalPort>
								<ipxact:name>SDI2</ipxact:name>
							</ipxact:logicalPort>
							<ipxact:physicalPort>
								<ipxact:name>spi_sdi2</ipxact:name>
							</ipxact:physicalPort>
						</ipxact:portMap>
						<ipxact:portMap>
							<ipxact:logicalPort>
								<ipxact:name>SDI3</ipxact:name>
							</ipxact:logicalPort>
							<ipxact:physicalPort>
								<ipxact:name>spi_sdi3</ipxact:name>
							</ipxact:physicalPort>
						</ipxact:portMap>
						<ipxact:portMap>
							<ipxact:logicalPort>
								<ipxact:name>MODE</ipxact:name>
							</ipxact:logicalPort>
							<ipxact:physicalPort>
								<ipxact:name>spi_mode</ipxact:name>
							</ipxact:physicalPort>
						</ipxact:portMap>
					</ipxact:portMaps>
				</ipxact:abstractionType>
			</ipxact:abstractionTypes>
			<ipxact:master/>
		</ipxact:busInterface>
		<ipxact:busInterface>
			<ipxact:name>spi_bus</ipxact:name>
			<ipxact:busType vendor="amba.com" library="AMBA3" name="APB" version="r1p0_4"/>
			<ipxact:abstractionTypes>
				<ipxact:abstractionType>
					<ipxact:abstractionRef vendor="amba.com" library="AMBA3" name="APB_rtl" version="r1p0_4"/>
					<ipxact:portMaps>
						<ipxact:portMap>
							<ipxact:logicalPort>
								<ipxact:name>PADDR</ipxact:name>
							</ipxact:logicalPort>
							<ipxact:physicalPort>
								<ipxact:name>PADDR</ipxact:name>
							</ipxact:physicalPort>
						</ipxact:portMap>
						<ipxact:portMap>
							<ipxact:logicalPort>
								<ipxact:name>PSELx</ipxact:name>
								<ipxact:range>
									<ipxact:left>0</ipxact:left>
									<ipxact:right>0</ipxact:right>
								</ipxact:range>
							</ipxact:logicalPort>
							<ipxact:physicalPort>
								<ipxact:name>PSEL</ipxact:name>
								<ipxact:partSelect>
									<ipxact:range>
										<ipxact:left>0</ipxact:left>
										<ipxact:right>0</ipxact:right>
									</ipxact:range>
								</ipxact:partSelect>
							</ipxact:physicalPort>
						</ipxact:portMap>
						<ipxact:portMap>
							<ipxact:logicalPort>
								<ipxact:name>PENABLE</ipxact:name>
								<ipxact:range>
									<ipxact:left>0</ipxact:left>
									<ipxact:right>0</ipxact:right>
								</ipxact:range>
							</ipxact:logicalPort>
							<ipxact:physicalPort>
								<ipxact:name>PENABLE</ipxact:name>
								<ipxact:partSelect>
									<ipxact:range>
										<ipxact:left>0</ipxact:left>
										<ipxact:right>0</ipxact:right>
									</ipxact:range>
								</ipxact:partSelect>
							</ipxact:physicalPort>
						</ipxact:portMap>
						<ipxact:portMap>
							<ipxact:logicalPort>
								<ipxact:name>PWRITE</ipxact:name>
								<ipxact:range>
									<ipxact:left>0</ipxact:left>
									<ipxact:right>0</ipxact:right>
								</ipxact:range>
							</ipxact:logicalPort>
							<ipxact:physicalPort>
								<ipxact:name>PWRITE</ipxact:name>
								<ipxact:partSelect>
									<ipxact:range>
										<ipxact:left>0</ipxact:left>
										<ipxact:right>0</ipxact:right>
									</ipxact:range>
								</ipxact:partSelect>
							</ipxact:physicalPort>
						</ipxact:portMap>
						<ipxact:portMap>
							<ipxact:logicalPort>
								<ipxact:name>PRDATA</ipxact:name>
							</ipxact:logicalPort>
							<ipxact:physicalPort>
								<ipxact:name>PRDATA</ipxact:name>
							</ipxact:physicalPort>
						</ipxact:portMap>
						<ipxact:portMap>
							<ipxact:logicalPort>
								<ipxact:name>PWDATA</ipxact:name>
							</ipxact:logicalPort>
							<ipxact:physicalPort>
								<ipxact:name>PWDATA</ipxact:name>
							</ipxact:physicalPort>
						</ipxact:portMap>
						<ipxact:portMap>
							<ipxact:logicalPort>
								<ipxact:name>PREADY</ipxact:name>
								<ipxact:range>
									<ipxact:left>0</ipxact:left>
									<ipxact:right>0</ipxact:right>
								</ipxact:range>
							</ipxact:logicalPort>
							<ipxact:physicalPort>
								<ipxact:name>PREADY</ipxact:name>
								<ipxact:partSelect>
									<ipxact:range>
										<ipxact:left>0</ipxact:left>
										<ipxact:right>0</ipxact:right>
									</ipxact:range>
								</ipxact:partSelect>
							</ipxact:physicalPort>
						</ipxact:portMap>
						<ipxact:portMap>
							<ipxact:logicalPort>
								<ipxact:name>PSLVERR</ipxact:name>
								<ipxact:range>
									<ipxact:left>0</ipxact:left>
									<ipxact:right>0</ipxact:right>
								</ipxact:range>
							</ipxact:logicalPort>
							<ipxact:physicalPort>
								<ipxact:name>PSLVERR</ipxact:name>
								<ipxact:partSelect>
									<ipxact:range>
										<ipxact:left>0</ipxact:left>
										<ipxact:right>0</ipxact:right>
									</ipxact:range>
								</ipxact:partSelect>
							</ipxact:physicalPort>
						</ipxact:portMap>
					</ipxact:portMaps>
				</ipxact:abstractionType>
			</ipxact:abstractionTypes>
			<ipxact:slave/>
		</ipxact:busInterface>
	</ipxact:busInterfaces>
	<ipxact:model>
		<ipxact:views>
			<ipxact:view>
				<ipxact:name>structural</ipxact:name>
				<ipxact:componentInstantiationRef>verilog_implementation</ipxact:componentInstantiationRef>
				<ipxact:designInstantiationRef>design</ipxact:designInstantiationRef>
				<ipxact:designConfigurationInstantiationRef>design_configuration</ipxact:designConfigurationInstantiationRef>
			</ipxact:view>
		</ipxact:views>
		<ipxact:instantiations>
			<ipxact:componentInstantiation>
				<ipxact:name>verilog_implementation</ipxact:name>
				<ipxact:language>Verilog</ipxact:language>
				<ipxact:moduleName>apb_spi_master</ipxact:moduleName>
				<ipxact:fileSetRef>
					<ipxact:localName>rtl</ipxact:localName>
				</ipxact:fileSetRef>
			</ipxact:componentInstantiation>
			<ipxact:designInstantiation>
				<ipxact:name>design</ipxact:name>
				<ipxact:designRef vendor="pulp-platform.org" library="peripheral" name="apb_spi_master.design" version="1.0">
					<ipxact:configurableElementValues>
						<ipxact:configurableElementValue referenceId="uuid_4e12fd67_766f_4e6a_a86a_46579c9b34e8">uuid_aef516b1_bf70_49fd_90ad_bc824602cb4a</ipxact:configurableElementValue>
						<ipxact:configurableElementValue referenceId="uuid_b05f2ffb_44f7_46ec_99c6_b14e989e003f">uuid_39b982e0_91a5_4ae9_a598_283f5197a4c9</ipxact:configurableElementValue>
					</ipxact:configurableElementValues>
				</ipxact:designRef>
			</ipxact:designInstantiation>
			<ipxact:designConfigurationInstantiation>
				<ipxact:name>design_configuration</ipxact:name>
				<ipxact:designConfigurationRef vendor="pulp-platform.org" library="peripheral" name="apb_spi_master.designcfg" version="1.0"/>
			</ipxact:designConfigurationInstantiation>
		</ipxact:instantiations>
		<ipxact:ports>
			<ipxact:port>
				<ipxact:name>events_o</ipxact:name>
				<ipxact:wire>
					<ipxact:direction>out</ipxact:direction>
					<ipxact:vectors>
						<ipxact:vector>
							<ipxact:left>1</ipxact:left>
							<ipxact:right>0</ipxact:right>
						</ipxact:vector>
					</ipxact:vectors>
					<ipxact:wireTypeDefs>
						<ipxact:wireTypeDef>
							<ipxact:typeName>logic</ipxact:typeName>
						</ipxact:wireTypeDef>
					</ipxact:wireTypeDefs>
				</ipxact:wire>
			</ipxact:port>
			<ipxact:port>
				<ipxact:name>spi_clk</ipxact:name>
				<ipxact:wire>
					<ipxact:direction>out</ipxact:direction>
					<ipxact:wireTypeDefs>
						<ipxact:wireTypeDef>
							<ipxact:typeName>logic</ipxact:typeName>
						</ipxact:wireTypeDef>
					</ipxact:wireTypeDefs>
				</ipxact:wire>
			</ipxact:port>
			<ipxact:port>
				<ipxact:name>spi_csn0</ipxact:name>
				<ipxact:wire>
					<ipxact:direction>out</ipxact:direction>
					<ipxact:wireTypeDefs>
						<ipxact:wireTypeDef>
							<ipxact:typeName>logic</ipxact:typeName>
						</ipxact:wireTypeDef>
					</ipxact:wireTypeDefs>
				</ipxact:wire>
			</ipxact:port>
			<ipxact:port>
				<ipxact:name>spi_csn1</ipxact:name>
				<ipxact:wire>
					<ipxact:direction>out</ipxact:direction>
					<ipxact:wireTypeDefs>
						<ipxact:wireTypeDef>
							<ipxact:typeName>logic</ipxact:typeName>
						</ipxact:wireTypeDef>
					</ipxact:wireTypeDefs>
				</ipxact:wire>
			</ipxact:port>
			<ipxact:port>
				<ipxact:name>spi_csn2</ipxact:name>
				<ipxact:wire>
					<ipxact:direction>out</ipxact:direction>
					<ipxact:wireTypeDefs>
						<ipxact:wireTypeDef>
							<ipxact:typeName>logic</ipxact:typeName>
						</ipxact:wireTypeDef>
					</ipxact:wireTypeDefs>
				</ipxact:wire>
			</ipxact:port>
			<ipxact:port>
				<ipxact:name>spi_csn3</ipxact:name>
				<ipxact:wire>
					<ipxact:direction>out</ipxact:direction>
					<ipxact:wireTypeDefs>
						<ipxact:wireTypeDef>
							<ipxact:typeName>logic</ipxact:typeName>
						</ipxact:wireTypeDef>
					</ipxact:wireTypeDefs>
				</ipxact:wire>
			</ipxact:port>
			<ipxact:port>
				<ipxact:name>spi_mode</ipxact:name>
				<ipxact:wire>
					<ipxact:direction>out</ipxact:direction>
					<ipxact:vectors>
						<ipxact:vector>
							<ipxact:left>1</ipxact:left>
							<ipxact:right>0</ipxact:right>
						</ipxact:vector>
					</ipxact:vectors>
					<ipxact:wireTypeDefs>
						<ipxact:wireTypeDef>
							<ipxact:typeName>logic</ipxact:typeName>
						</ipxact:wireTypeDef>
					</ipxact:wireTypeDefs>
				</ipxact:wire>
			</ipxact:port>
			<ipxact:port>
				<ipxact:name>spi_sdo0</ipxact:name>
				<ipxact:wire>
					<ipxact:direction>out</ipxact:direction>
					<ipxact:wireTypeDefs>
						<ipxact:wireTypeDef>
							<ipxact:typeName>logic</ipxact:typeName>
						</ipxact:wireTypeDef>
					</ipxact:wireTypeDefs>
				</ipxact:wire>
			</ipxact:port>
			<ipxact:port>
				<ipxact:name>spi_sdo1</ipxact:name>
				<ipxact:wire>
					<ipxact:direction>out</ipxact:direction>
					<ipxact:wireTypeDefs>
						<ipxact:wireTypeDef>
							<ipxact:typeName>logic</ipxact:typeName>
						</ipxact:wireTypeDef>
					</ipxact:wireTypeDefs>
				</ipxact:wire>
			</ipxact:port>
			<ipxact:port>
				<ipxact:name>spi_sdo2</ipxact:name>
				<ipxact:wire>
					<ipxact:direction>out</ipxact:direction>
					<ipxact:wireTypeDefs>
						<ipxact:wireTypeDef>
							<ipxact:typeName>logic</ipxact:typeName>
						</ipxact:wireTypeDef>
					</ipxact:wireTypeDefs>
				</ipxact:wire>
			</ipxact:port>
			<ipxact:port>
				<ipxact:name>spi_sdo3</ipxact:name>
				<ipxact:wire>
					<ipxact:direction>out</ipxact:direction>
					<ipxact:wireTypeDefs>
						<ipxact:wireTypeDef>
							<ipxact:typeName>logic</ipxact:typeName>
						</ipxact:wireTypeDef>
					</ipxact:wireTypeDefs>
				</ipxact:wire>
			</ipxact:port>
			<ipxact:port>
				<ipxact:name>spi_sdi0</ipxact:name>
				<ipxact:wire>
					<ipxact:direction>in</ipxact:direction>
					<ipxact:wireTypeDefs>
						<ipxact:wireTypeDef>
							<ipxact:typeName>logic</ipxact:typeName>
						</ipxact:wireTypeDef>
					</ipxact:wireTypeDefs>
				</ipxact:wire>
			</ipxact:port>
			<ipxact:port>
				<ipxact:name>spi_sdi1</ipxact:name>
				<ipxact:wire>
					<ipxact:direction>in</ipxact:direction>
					<ipxact:wireTypeDefs>
						<ipxact:wireTypeDef>
							<ipxact:typeName>logic</ipxact:typeName>
						</ipxact:wireTypeDef>
					</ipxact:wireTypeDefs>
				</ipxact:wire>
			</ipxact:port>
			<ipxact:port>
				<ipxact:name>spi_sdi2</ipxact:name>
				<ipxact:wire>
					<ipxact:direction>in</ipxact:direction>
					<ipxact:wireTypeDefs>
						<ipxact:wireTypeDef>
							<ipxact:typeName>logic</ipxact:typeName>
						</ipxact:wireTypeDef>
					</ipxact:wireTypeDefs>
				</ipxact:wire>
			</ipxact:port>
			<ipxact:port>
				<ipxact:name>spi_sdi3</ipxact:name>
				<ipxact:wire>
					<ipxact:direction>in</ipxact:direction>
					<ipxact:wireTypeDefs>
						<ipxact:wireTypeDef>
							<ipxact:typeName>logic</ipxact:typeName>
						</ipxact:wireTypeDef>
					</ipxact:wireTypeDefs>
				</ipxact:wire>
			</ipxact:port>
			<ipxact:port>
				<ipxact:name>HCLK</ipxact:name>
				<ipxact:wire>
					<ipxact:direction>in</ipxact:direction>
					<ipxact:wireTypeDefs>
						<ipxact:wireTypeDef>
							<ipxact:typeName>logic</ipxact:typeName>
						</ipxact:wireTypeDef>
					</ipxact:wireTypeDefs>
				</ipxact:wire>
				<ipxact:vendorExtensions>
					<kactus2:adHocVisible/>
					<kactus2:position x="-110" y="30"/>
				</ipxact:vendorExtensions>
			</ipxact:port>
			<ipxact:port>
				<ipxact:name>HRESETn</ipxact:name>
				<ipxact:wire>
					<ipxact:direction>in</ipxact:direction>
					<ipxact:wireTypeDefs>
						<ipxact:wireTypeDef>
							<ipxact:typeName>logic</ipxact:typeName>
						</ipxact:wireTypeDef>
					</ipxact:wireTypeDefs>
				</ipxact:wire>
				<ipxact:vendorExtensions>
					<kactus2:adHocVisible/>
					<kactus2:position x="-110" y="50"/>
				</ipxact:vendorExtensions>
			</ipxact:port>
			<ipxact:port>
				<ipxact:name>PADDR</ipxact:name>
				<ipxact:wire>
					<ipxact:direction>in</ipxact:direction>
					<ipxact:vectors>
						<ipxact:vector>
							<ipxact:left>uuid_39b982e0_91a5_4ae9_a598_283f5197a4c9-1</ipxact:left>
							<ipxact:right>0</ipxact:right>
						</ipxact:vector>
					</ipxact:vectors>
					<ipxact:wireTypeDefs>
						<ipxact:wireTypeDef>
							<ipxact:typeName>logic</ipxact:typeName>
						</ipxact:wireTypeDef>
					</ipxact:wireTypeDefs>
				</ipxact:wire>
			</ipxact:port>
			<ipxact:port>
				<ipxact:name>PWDATA</ipxact:name>
				<ipxact:wire>
					<ipxact:direction>in</ipxact:direction>
					<ipxact:vectors>
						<ipxact:vector>
							<ipxact:left>31</ipxact:left>
							<ipxact:right>0</ipxact:right>
						</ipxact:vector>
					</ipxact:vectors>
					<ipxact:wireTypeDefs>
						<ipxact:wireTypeDef>
							<ipxact:typeName>logic</ipxact:typeName>
						</ipxact:wireTypeDef>
					</ipxact:wireTypeDefs>
				</ipxact:wire>
			</ipxact:port>
			<ipxact:port>
				<ipxact:name>PWRITE</ipxact:name>
				<ipxact:wire>
					<ipxact:direction>in</ipxact:direction>
					<ipxact:wireTypeDefs>
						<ipxact:wireTypeDef>
							<ipxact:typeName>logic</ipxact:typeName>
						</ipxact:wireTypeDef>
					</ipxact:wireTypeDefs>
				</ipxact:wire>
			</ipxact:port>
			<ipxact:port>
				<ipxact:name>PSEL</ipxact:name>
				<ipxact:wire>
					<ipxact:direction>in</ipxact:direction>
					<ipxact:wireTypeDefs>
						<ipxact:wireTypeDef>
							<ipxact:typeName>logic</ipxact:typeName>
						</ipxact:wireTypeDef>
					</ipxact:wireTypeDefs>
				</ipxact:wire>
			</ipxact:port>
			<ipxact:port>
				<ipxact:name>PENABLE</ipxact:name>
				<ipxact:wire>
					<ipxact:direction>in</ipxact:direction>
					<ipxact:wireTypeDefs>
						<ipxact:wireTypeDef>
							<ipxact:typeName>logic</ipxact:typeName>
						</ipxact:wireTypeDef>
					</ipxact:wireTypeDefs>
				</ipxact:wire>
			</ipxact:port>
			<ipxact:port>
				<ipxact:name>PRDATA</ipxact:name>
				<ipxact:wire>
					<ipxact:direction>out</ipxact:direction>
					<ipxact:vectors>
						<ipxact:vector>
							<ipxact:left>31</ipxact:left>
							<ipxact:right>0</ipxact:right>
						</ipxact:vector>
					</ipxact:vectors>
					<ipxact:wireTypeDefs>
						<ipxact:wireTypeDef>
							<ipxact:typeName>logic</ipxact:typeName>
						</ipxact:wireTypeDef>
					</ipxact:wireTypeDefs>
				</ipxact:wire>
			</ipxact:port>
			<ipxact:port>
				<ipxact:name>PREADY</ipxact:name>
				<ipxact:wire>
					<ipxact:direction>out</ipxact:direction>
					<ipxact:wireTypeDefs>
						<ipxact:wireTypeDef>
							<ipxact:typeName>logic</ipxact:typeName>
						</ipxact:wireTypeDef>
					</ipxact:wireTypeDefs>
				</ipxact:wire>
			</ipxact:port>
			<ipxact:port>
				<ipxact:name>PSLVERR</ipxact:name>
				<ipxact:wire>
					<ipxact:direction>out</ipxact:direction>
					<ipxact:wireTypeDefs>
						<ipxact:wireTypeDef>
							<ipxact:typeName>logic</ipxact:typeName>
						</ipxact:wireTypeDef>
					</ipxact:wireTypeDefs>
				</ipxact:wire>
			</ipxact:port>
		</ipxact:ports>
	</ipxact:model>
	<ipxact:fileSets>
		<ipxact:fileSet>
			<ipxact:name>rtl</ipxact:name>
			<ipxact:file>
				<ipxact:name>../../../../../pulpino/ips/apb/apb_spi_master/apb_spi_master.sv</ipxact:name>
				<ipxact:fileType>systemVerilogSource</ipxact:fileType>
				<ipxact:isStructural>true</ipxact:isStructural>
				<ipxact:vendorExtensions>
					<kactus2:hash>d41d8cd98f00b204e9800998ecf8427e</kactus2:hash>
				</ipxact:vendorExtensions>
			</ipxact:file>
			<ipxact:file>
				<ipxact:name>../../../../../pulpino/ips/apb/apb_spi_master/README.md</ipxact:name>
				<ipxact:fileType>unknown</ipxact:fileType>
				<ipxact:vendorExtensions>
					<kactus2:hash>d41d8cd98f00b204e9800998ecf8427e</kactus2:hash>
				</ipxact:vendorExtensions>
			</ipxact:file>
			<ipxact:file>
				<ipxact:name>../../../../../pulpino/ips/apb/apb_spi_master/spi_master_apb_if.sv</ipxact:name>
				<ipxact:fileType>systemVerilogSource</ipxact:fileType>
				<ipxact:vendorExtensions>
					<kactus2:hash>d41d8cd98f00b204e9800998ecf8427e</kactus2:hash>
				</ipxact:vendorExtensions>
			</ipxact:file>
			<ipxact:file>
				<ipxact:name>../../../../../pulpino/ips/apb/apb_spi_master/src_files.yml</ipxact:name>
				<ipxact:fileType>unknown</ipxact:fileType>
				<ipxact:vendorExtensions>
					<kactus2:hash>d41d8cd98f00b204e9800998ecf8427e</kactus2:hash>
				</ipxact:vendorExtensions>
			</ipxact:file>
		</ipxact:fileSet>
	</ipxact:fileSets>
	<ipxact:parameters>
		<ipxact:parameter kactus2:usageCount="2" parameterId="uuid_39b982e0_91a5_4ae9_a598_283f5197a4c9">
			<ipxact:name>APB_ADDR_WIDTH</ipxact:name>
			<ipxact:value>12</ipxact:value>
		</ipxact:parameter>
		<ipxact:parameter kactus2:usageCount="1" parameterId="uuid_aef516b1_bf70_49fd_90ad_bc824602cb4a" resolve="user">
			<ipxact:name>BUFFER_DEPTH</ipxact:name>
			<ipxact:value>10</ipxact:value>
		</ipxact:parameter>
	</ipxact:parameters>
	<ipxact:vendorExtensions>
		<kactus2:author>pekkarie</kactus2:author>
		<kactus2:version>3,4,189,0</kactus2:version>
		<kactus2:kts_attributes>
			<kactus2:kts_productHier>Flat</kactus2:kts_productHier>
			<kactus2:kts_implementation>HW</kactus2:kts_implementation>
			<kactus2:kts_firmness>Mutable</kactus2:kts_firmness>
		</kactus2:kts_attributes>
		<kactus2:license>solderpad</kactus2:license>
	</ipxact:vendorExtensions>
</ipxact:component>
